{"name":"Light","description":"The Evil wizard found a way trap the gods into sculptures. \nHe now Harvests their energy, but the Monsters, which the gods sent out to him were still there but ow out of control","quests":[{"uuid":"2c7d53c0-0c60-48ae-9789-956aae6c2b3d","name":"The Fey Crafter","description":"  ","x":79,"y":160,"icon":{"id":"roots:fey_crafter"},"prerequisites":["686448b5-ea21-4f9b-9865-f75977c22a8c"],"tasks":[{"type":"DETECT","items":[{"item":{"id":"roots:fey_crafter"}},{"item":{"id":"roots:elemental_soil"},"required":4}]}],"reward":[{"id":"ancientwarfarenpc:coin","amount":10,"nbt":"{metal:\"gold\"}"}],"commandrewards":[]},{"uuid":"3d9487ed-d2f8-431f-a9db-3e9e162900b7","name":"Hermine Danger","description":" ","x":156,"y":134,"icon":{"id":"ebwizardry:apprentice_wand"},"prerequisites":["b981b6f3-0be5-4068-a244-077fb4bb7132"],"tasks":[{"type":"DETECT","items":[{"item":{"id":"ebwizardry:apprentice_wand"}},{"item":{"id":"ebwizardry:apprentice_fire_wand"}},{"item":{"id":"ebwizardry:apprentice_ice_wand"}},{"item":{"id":"ebwizardry:apprentice_lightning_wand"}},{"item":{"id":"ebwizardry:apprentice_necromancy_wand"}},{"item":{"id":"ebwizardry:apprentice_earth_wand"}},{"item":{"id":"ebwizardry:apprentice_sorcery_wand"}},{"item":{"id":"ebwizardry:apprentice_healing_wand"}}]}],"reward":[{"id":"hardcorequesting:bags","damage":1,"amount":4}],"commandrewards":[]},{"uuid":"2d4a0c08-6b46-44b7-8db6-6db5c137552f","name":"Star Wars IV","x":264,"y":67,"icon":{"id":"astralsorcery:blockaltar","damage":3},"prerequisites":["a93aa995-f298-4c19-a793-56f29aa2ad81","3fd4917f-7e91-4321-8f89-9f25fbc95a93"],"tasks":[{"type":"DETECT","items":[{"item":{"id":"astralsorcery:blockaltar","damage":3}}]}],"reward":[{"id":"hardcorequesting:bags","damage":1}],"commandrewards":[]},{"uuid":"f587b69f-9247-43b5-ad67-3fbea905553d","name":"Shamanic Magic I","description":" ","x":34,"y":150,"icon":{"id":"roots:spell_dust","nbt":"{spell_holder:{spell_0:\"spell_sky_soarer\",selectedSlot:0,lastCooldown:0,cooldown:0}}"},"prerequisites":["686448b5-ea21-4f9b-9865-f75977c22a8c"],"tasks":[{"type":"CONSUME","items":[{"item":{"id":"roots:spell_dust","nbt":"{spell_holder:{spell_0:\"spell_sky_soarer\",selectedSlot:0,lastCooldown:0,cooldown:0}}"}},{"item":{"id":"roots:spell_dust","nbt":"{spell_holder:{spell_0:\"spell_second_wind\",selectedSlot:0,lastCooldown:0,cooldown:0}}"}},{"item":{"id":"roots:spell_dust","nbt":"{spell_holder:{spell_0:\"spell_sanctuary\",selectedSlot:0,lastCooldown:0,cooldown:0}}"}},{"item":{"id":"roots:spell_dust","nbt":"{spell_holder:{spell_0:\"spell_rampant_growth\",selectedSlot:0,lastCooldown:0,cooldown:0}}"}},{"item":{"id":"roots:spell_dust","nbt":"{spell_holder:{spell_0:\"spell_shatter\",selectedSlot:0,lastCooldown:0,cooldown:0}}"}},{"item":{"id":"roots:spell_dust","nbt":"{spell_holder:{spell_0:\"spell_magnetism\",selectedSlot:0,lastCooldown:0,cooldown:0}}"}},{"item":{"id":"roots:spell_dust","nbt":"{spell_holder:{spell_0:\"spell_wild_fire\",selectedSlot:0,lastCooldown:0,cooldown:0}}"}},{"item":{"id":"roots:spell_dust","nbt":"{spell_holder:{spell_0:\"spell_life_drain\",selectedSlot:0,lastCooldown:0,cooldown:0}}"}}]}],"reward":[{"id":"ancientwarfarenpc:coin","amount":6,"nbt":"{metal:\"gold\"}"}],"commandrewards":[]},{"uuid":"a93aa995-f298-4c19-a793-56f29aa2ad81","name":"The Twilight Forest","description":"Take this to enter the Twilight Forrest","x":243,"y":91,"icon":{"id":"twilightforest:miniature_structure"},"prerequisites":["c49b9058-489e-4efe-9b2a-c2b77bea3949"],"tasks":[{"type":"DETECT","items":[{"item":{"id":"astralsorcery:itemcraftingcomponent","damage":1}}]}],"reward":[{"id":"hardcorequesting:bags","damage":1}],"commandrewards":[]},{"uuid":"a3c8020f-bd50-4aff-99f1-016a1824345a","name":"Earth","description":" ","x":81,"y":186,"icon":{"id":"roots:elemental_soil_earth"},"prerequisites":["2c7d53c0-0c60-48ae-9789-956aae6c2b3d"],"tasks":[{"type":"DETECT","items":[{"item":{"id":"roots:elemental_soil_earth"}}]}],"reward":[{"id":"ancientwarfarenpc:coin","amount":5,"nbt":"{metal:\"gold\"}"}],"commandrewards":[]},{"uuid":"58ceaf04-f350-43b7-9286-f0be506a79b2","name":"Stairway to Heaven","description":" ","x":131,"y":134,"icon":{"id":"aether_legacy:golden_amber"},"prerequisites":["6caade95-1d12-41ac-b0a3-b2d962717e59"],"tasks":[{"type":"CONSUME","items":[{"item":{"id":"aether_legacy:aether_log"},"required":32},{"item":{"id":"aether_legacy:holystone"},"required":32}]}],"reward":[{"id":"hardcorequesting:bags","damage":1}],"commandrewards":[]},{"uuid":"b981b6f3-0be5-4068-a244-077fb4bb7132","name":"Ron Weasely","description":" ","x":120,"y":113,"icon":{"id":"ebwizardry:magic_wand"},"prerequisites":["8298dd13-3b9d-44cb-9160-77eb4db0ac5b"],"tasks":[{"type":"DETECT","items":[{"item":{"id":"ebwizardry:magic_wand"}},{"item":{"id":"ebwizardry:novice_fire_wand"}},{"item":{"id":"ebwizardry:novice_ice_wand"}},{"item":{"id":"ebwizardry:novice_lightning_wand"}},{"item":{"id":"ebwizardry:novice_necromancy_wand"}},{"item":{"id":"ebwizardry:novice_earth_wand"}},{"item":{"id":"ebwizardry:novice_sorcery_wand"}},{"item":{"id":"ebwizardry:novice_healing_wand"}}]}],"reward":[{"id":"hardcorequesting:bags","damage":1,"amount":3}],"commandrewards":[]},{"uuid":"3fd4917f-7e91-4321-8f89-9f25fbc95a93","name":"fairly odd parents","description":" ","x":232,"y":70,"icon":{"id":"botania:alfheimportal"},"prerequisites":["c49b9058-489e-4efe-9b2a-c2b77bea3949"],"tasks":[{"type":"DETECT","items":[{"item":{"id":"botania:alfheimportal"}}]}],"reward":[{"id":"hardcorequesting:bags","damage":1}],"commandrewards":[]},{"uuid":"b7cfdc25-189e-401d-af22-6ff3c0255cd0","name":"Terraria","description":" ","x":281,"y":55,"icon":{"id":"botania:terrasteelchest"},"prerequisites":["2d4a0c08-6b46-44b7-8db6-6db5c137552f"],"tasks":[{"type":"DETECT","items":[{"item":{"id":"botania:terrasteelhelmreveal"}},{"item":{"id":"botania:terrasteelchest"}},{"item":{"id":"botania:terrasteellegs"}},{"item":{"id":"botania:terrasteelboots"}}]}],"reward":[{"id":"hardcorequesting:bags","damage":1}],"commandrewards":[]},{"uuid":"d9299760-d4c6-4863-87ab-1def93f43d32","name":"Water","description":" ","x":56,"y":149,"icon":{"id":"roots:elemental_soil_water"},"prerequisites":["2c7d53c0-0c60-48ae-9789-956aae6c2b3d"],"tasks":[{"type":"DETECT","items":[{"item":{"id":"roots:elemental_soil_water"}}]}],"reward":[{"id":"ancientwarfarenpc:coin","amount":5,"nbt":"{metal:\"gold\"}"}],"commandrewards":[]},{"uuid":"3a518125-d97e-4af2-9c80-85ba998be4f8","name":"Harry Propper","description":" ","x":167,"y":114,"icon":{"id":"ebwizardry:master_wand"},"prerequisites":["dfcb2210-1870-428e-b47f-dbed435e8b33"],"tasks":[{"type":"DETECT","items":[{"item":{"id":"ebwizardry:master_wand"}},{"item":{"id":"ebwizardry:master_fire_wand"}},{"item":{"id":"ebwizardry:master_ice_wand"}},{"item":{"id":"ebwizardry:master_lightning_wand"}},{"item":{"id":"ebwizardry:master_necromancy_wand"}},{"item":{"id":"ebwizardry:master_earth_wand"}},{"item":{"id":"ebwizardry:master_sorcery_wand"}},{"item":{"id":"ebwizardry:master_healing_wand"}}]}],"reward":[{"id":"hardcorequesting:bags","damage":1,"amount":6}],"commandrewards":[]},{"uuid":"9173234c-8812-4b4b-b681-6e6635314c62","name":"Air","description":" ","x":88,"y":135,"icon":{"id":"roots:elemental_soil_air"},"prerequisites":["2c7d53c0-0c60-48ae-9789-956aae6c2b3d"],"tasks":[{"type":"DETECT","items":[{"item":{"id":"roots:elemental_soil_air"}}]}],"reward":[{"id":"ancientwarfarenpc:coin","amount":5,"nbt":"{metal:\"gold\"}"}],"commandrewards":[]},{"uuid":"6caade95-1d12-41ac-b0a3-b2d962717e59","name":"To the stars","description":" ","x":109,"y":146,"icon":{"id":"astralsorcery:blockaltar"},"prerequisites":["2c7d53c0-0c60-48ae-9789-956aae6c2b3d"],"tasks":[{"type":"DETECT","items":[{"item":{"id":"astralsorcery:blockaltar"}}]}],"reward":[{"id":"hardcorequesting:bags","damage":1}],"commandrewards":[]},{"uuid":"ae6f0ebb-6bdb-4814-84c6-89658dc33c6e","name":"Naturally","description":"In the fight against the dark forces, you must first learn natural magic","x":24,"y":186,"icon":{"id":"roots:iron_knife"},"prerequisites":["179820a3-2438-4bd9-bb89-bed4e148983a"],"tasks":[{"type":"DETECT","items":[{"item":{"id":"roots:bark_oak"},"required":16},{"item":{"id":"roots:terra_moss"},"required":16},{"item":{"id":"roots:iron_knife"}}]}],"reward":[{"id":"ancientwarfarenpc:coin","amount":5,"nbt":"{metal:\"gold\"}"}],"commandrewards":[]},{"uuid":"71765717-80ce-4b60-876a-a9eaddbda6c4","name":"Elvis Presly Dumb","description":" ","x":190,"y":100,"icon":{"id":"arcane_essentials:master_lightning_sword"},"prerequisites":["3a518125-d97e-4af2-9c80-85ba998be4f8"],"tasks":[{"type":"DETECT","items":[{"item":{"id":"arcane_essentials:master_lightning_sword"}},{"item":{"id":"arcane_essentials:master_sorcery_sword"}},{"item":{"id":"arcane_essentials:master_nature_sword"}},{"item":{"id":"arcane_essentials:master_necromancy_sword"}},{"item":{"id":"arcane_essentials:master_fire_sword"}},{"item":{"id":"arcane_essentials:master_ice_sword"}},{"item":{"id":"arcane_essentials:master_healing_sword"}}]}],"reward":[{"id":"hardcorequesting:bags","damage":1,"amount":6}],"commandrewards":[]},{"uuid":"686448b5-ea21-4f9b-9865-f75977c22a8c","name":"Entry with the shamans","description":" ","x":52,"y":174,"icon":{"id":"roots:staff"},"prerequisites":["ae6f0ebb-6bdb-4814-84c6-89658dc33c6e"],"tasks":[{"type":"DETECT","items":[{"item":{"id":"roots:imbuer"}},{"item":{"id":"roots:bonfire"}},{"item":{"id":"roots:staff"}},{"item":{"id":"roots:spell_dust","nbt":"{spell_holder:{spell_0:\"spell_supplication\",selectedSlot:0,lastCooldown:0,cooldown:0}}"}},{"item":{"id":"roots:grove_stone"}}]}],"reward":[{"id":"ancientwarfarenpc:coin","amount":5,"nbt":"{metal:\"gold\"}"}],"commandrewards":[]},{"uuid":"f6e50764-a98d-40d3-94c0-eca8bb5dbc73","name":"Shamanic Magic II","description":" ","x":33,"y":124,"icon":{"id":"roots:spell_dust","nbt":"{spell_holder:{spell_0:\"spell_sense_animals\",selectedSlot:0,lastCooldown:0,cooldown:0}}"},"prerequisites":["f587b69f-9247-43b5-ad67-3fbea905553d"],"tasks":[{"type":"CONSUME","items":[{"item":{"id":"roots:spell_dust","nbt":"{spell_holder:{spell_0:\"spell_sense_animals\",selectedSlot:0,lastCooldown:0,cooldown:0}}"}},{"item":{"id":"roots:spell_dust","nbt":"{spell_holder:{spell_0:\"spell_dandelion_winds\",selectedSlot:0,lastCooldown:0,cooldown:0}}"}},{"item":{"id":"roots:spell_dust","nbt":"{spell_holder:{spell_0:\"spell_growth_infusion\",selectedSlot:0,lastCooldown:0,cooldown:0}}"}},{"item":{"id":"roots:spell_dust","nbt":"{spell_holder:{spell_0:\"spell_harvest\",selectedSlot:0,lastCooldown:0,cooldown:0}}"}},{"item":{"id":"roots:spell_dust","nbt":"{spell_holder:{spell_0:\"spell_petal_shell\",selectedSlot:0,lastCooldown:0,cooldown:0}}"}},{"item":{"id":"roots:spell_dust","nbt":"{spell_holder:{spell_0:\"spell_radiance\",selectedSlot:0,lastCooldown:0,cooldown:0}}"}},{"item":{"id":"roots:spell_dust","nbt":"{spell_holder:{spell_0:\"spell_time_stop\",selectedSlot:0,lastCooldown:0,cooldown:0}}"}},{"item":{"id":"roots:spell_dust","nbt":"{spell_holder:{spell_0:\"spell_sense_danger\",selectedSlot:0,lastCooldown:0,cooldown:0}}"}},{"item":{"id":"roots:spell_dust","nbt":"{spell_holder:{spell_0:\"spell_geas\",selectedSlot:0,lastCooldown:0,cooldown:0}}"}}]}],"reward":[{"id":"ancientwarfarenpc:coin","amount":7,"nbt":"{metal:\"gold\"}"}],"commandrewards":[]},{"uuid":"dfcb2210-1870-428e-b47f-dbed435e8b33","name":"Tom Middle","description":" ","x":144,"y":113,"icon":{"id":"ebwizardry:advanced_wand"},"prerequisites":["3d9487ed-d2f8-431f-a9db-3e9e162900b7"],"tasks":[{"type":"DETECT","items":[{"item":{"id":"ebwizardry:advanced_wand"}},{"item":{"id":"ebwizardry:advanced_fire_wand"}},{"item":{"id":"ebwizardry:advanced_ice_wand"}},{"item":{"id":"ebwizardry:advanced_lightning_wand"}},{"item":{"id":"ebwizardry:advanced_necromancy_wand"}},{"item":{"id":"ebwizardry:advanced_earth_wand"}},{"item":{"id":"ebwizardry:advanced_sorcery_wand"}},{"item":{"id":"ebwizardry:advanced_healing_wand"}}]}],"reward":[{"id":"hardcorequesting:bags","damage":1,"amount":5}],"commandrewards":[]},{"uuid":"8298dd13-3b9d-44cb-9160-77eb4db0ac5b","name":"Star Wars II","description":" ","x":140,"y":156,"icon":{"id":"astralsorcery:blockaltar","damage":1},"prerequisites":["58ceaf04-f350-43b7-9286-f0be506a79b2"],"tasks":[{"type":"DETECT","items":[{"item":{"id":"astralsorcery:blockaltar","damage":1}}]}],"reward":[{"id":"hardcorequesting:bags","damage":1,"amount":2}],"commandrewards":[]},{"uuid":"c49b9058-489e-4efe-9b2a-c2b77bea3949","name":"Star Wars III","description":" ","x":212,"y":85,"icon":{"id":"astralsorcery:blockaltar","damage":2},"prerequisites":["71765717-80ce-4b60-876a-a9eaddbda6c4"],"tasks":[{"type":"DETECT","items":[{"item":{"id":"astralsorcery:blockaltar","damage":2}}]}],"reward":[{"id":"hardcorequesting:bags","damage":1}],"commandrewards":[]},{"uuid":"ad77e96f-1b27-461c-be9e-3f0719a6a642","name":"Fire","description":" ","x":103,"y":171,"icon":{"id":"roots:elemental_soil_fire"},"prerequisites":["2c7d53c0-0c60-48ae-9789-956aae6c2b3d"],"tasks":[{"type":"DETECT","items":[{"item":{"id":"roots:elemental_soil_fire"}}]}],"reward":[{"id":"ancientwarfarenpc:coin","amount":5,"nbt":"{metal:\"gold\"}"}],"commandrewards":[]},{"uuid":"f925cf66-c078-4dd4-b6ab-8e26f53ee6c3","name":"Shamanic Magic III","description":" ","x":31,"y":90,"icon":{"id":"roots:spell_dust","nbt":"{spell_holder:{spell_0:\"spell_sense_animals\",selectedSlot:0,lastCooldown:0,cooldown:0}}"},"prerequisites":["f6e50764-a98d-40d3-94c0-eca8bb5dbc73"],"tasks":[{"type":"CONSUME","items":[{"item":{"id":"roots:spell_dust","nbt":"{spell_holder:{spell_0:\"spell_iced_touch\",selectedSlot:0,lastCooldown:0,cooldown:0}}"}},{"item":{"id":"roots:spell_dust","nbt":"{spell_holder:{spell_0:\"spell_rose_thorns\",selectedSlot:0,lastCooldown:0,cooldown:0}}"}},{"item":{"id":"roots:spell_dust","nbt":"{spell_holder:{spell_0:\"spell_acid_cloud\",selectedSlot:0,lastCooldown:0,cooldown:0}}"}},{"item":{"id":"roots:spell_dust","nbt":"{spell_holder:{spell_0:\"spell_light_drifter\",selectedSlot:0,lastCooldown:0,cooldown:0}}"}},{"item":{"id":"roots:spell_dust","nbt":"{spell_holder:{spell_0:\"spell_supplication\",selectedSlot:0,lastCooldown:0,cooldown:0}}"}},{"item":{"id":"roots:spell_dust","nbt":"{spell_holder:{spell_0:\"spell_fey_light\",selectedSlot:0,lastCooldown:0,cooldown:0}}"}}]}],"reward":[{"id":"ancientwarfarenpc:coin","amount":8,"nbt":"{metal:\"gold\"}"}],"commandrewards":[]}],"reputationBar":[]}